<mujoco model="conveyor_box_system">
  <compiler angle="radian" coordinate="local" inertiafromgeom="true" />
  <option timestep="0.01" gravity="0 0 -9.81" integrator="RK4" />
  <asset>
    <material name="box_material" rgba="0.8 0.6 0.4 1" />
    <material name="conveyor_material" rgba="0.3 0.3 0.3 1" />
    <material name="object_material" rgba="0.2 0.8 0.2 1" />
    <material name="ground_material" rgba="0.9 0.9 0.9 1" />
    <material name="wall_material" rgba="0.7 0.7 0.8 1" />
    <texture name="grid" type="2d" builtin="checker" rgb1="0.1 0.2 0.3" rgb2="0.2 0.3 0.4" width="300" height="300" />
    <material name="grid_material" texture="grid" texrepeat="8 8" rgba="0.8 0.8 0.8 1" />
  <mesh name="obj_0" file="g:\irregularBPP\dataset\objaversestl\stockpart.stl" scale="0.01 0.01 0.01" /><mesh name="obj_1" file="g:\irregularBPP\dataset\objaversestl\picatny.stl" scale="0.01 0.01 0.01" /><mesh name="obj_2" file="g:\irregularBPP\dataset\objaversestl\stockpart.stl" scale="0.01 0.01 0.01" /><mesh name="obj_3" file="g:\irregularBPP\dataset\objaversestl\single_joycon_grip+.STL" scale="0.01 0.01 0.01" /><mesh name="obj_4" file="g:\irregularBPP\dataset\objaversestl\HANDLE_ENDER_3_mount.stl" scale="0.01 0.01 0.01" /><mesh name="obj_5" file="g:\irregularBPP\dataset\objaversestl\nuts_lock.stl" scale="0.01 0.01 0.01" /><mesh name="obj_6" file="g:\irregularBPP\dataset\objaversestl\licenceplate_20221103-47-161k5q3.stl" scale="0.01 0.01 0.01" /><mesh name="obj_7" file="g:\irregularBPP\dataset\objaversestl\ShroomEyeRemix.stl" scale="0.01 0.01 0.01" /><mesh name="obj_8" file="g:\irregularBPP\dataset\objaversestl\picatiny_mount_15.stl" scale="0.01 0.01 0.01" /><mesh name="obj_9" file="g:\irregularBPP\dataset\objaversestl\SBF_FOXHOUND_HANDGUARD_1.1.stl" scale="0.01 0.01 0.01" /><mesh name="obj_10" file="g:\irregularBPP\dataset\objaversestl\picatny.stl" scale="0.01 0.01 0.01" /><mesh name="obj_11" file="g:\irregularBPP\dataset\objaversestl\picatny.stl" scale="0.01 0.01 0.01" /><mesh name="obj_12" file="g:\irregularBPP\dataset\objaversestl\single_joycon_grip-.STL" scale="0.01 0.01 0.01" /><mesh name="obj_13" file="g:\irregularBPP\dataset\objaversestl\single_joycon_grip-.STL" scale="0.01 0.01 0.01" /><mesh name="obj_14" file="g:\irregularBPP\dataset\objaversestl\hd_font_keychain_v4_2_20220926-41-1k46e5j.stl" scale="0.01 0.01 0.01" /><mesh name="obj_15" file="g:\irregularBPP\dataset\objaversestl\quest_stock_.stl" scale="0.01 0.01 0.01" /><mesh name="obj_16" file="g:\irregularBPP\dataset\objaversestl\protetor_de_tomada.stl" scale="0.01 0.01 0.01" /><mesh name="obj_17" file="g:\irregularBPP\dataset\objaversestl\ShroomEyeRemix.stl" scale="0.01 0.01 0.01" /><mesh name="obj_18" file="g:\irregularBPP\dataset\objaversestl\HANDLE_ENDER_3_mount_rt.stl" scale="0.01 0.01 0.01" /><mesh name="obj_19" file="g:\irregularBPP\dataset\objaversestl\protetor_de_tomada.stl" scale="0.01 0.01 0.01" /><mesh name="obj_20" file="g:\irregularBPP\dataset\objaversestl\HANDLE_ENDER_3_mount.stl" scale="0.01 0.01 0.01" /><mesh name="obj_21" file="g:\irregularBPP\dataset\objaversestl\ShroomCapRemix.stl" scale="0.01 0.01 0.01" /></asset>
  <worldbody>
    <geom name="ground" type="plane" size="10 10 0.1" material="grid_material" />
    <body name="collection_box" pos="0 0 0.1">
      <geom name="box_bottom" type="box" size="1.5 1.5 0.05" material="box_material" />
      <geom name="box_wall1" type="box" size="1.5 0.05 0.8" pos="0 1.45 0.25" material="wall_material" />
      <geom name="box_wall2" type="box" size="1.5 0.05 0.8" pos="0 -1.45 0.25" material="wall_material" />
      <geom name="box_wall3" type="box" size="0.05 1.4 0.8" pos="1.45 0 0.25" material="wall_material" />
      <geom name="box_wall4" type="box" size="0.05 1.4 0.8" pos="-1.45 0 0.25" material="wall_material" />
    </body>
    <light name="main_light" pos="0 0 10" dir="0 0 -1" diffuse="0.8 0.8 0.8" specular="0.2 0.2 0.2" />
    <light name="side_light" pos="5 5 5" dir="-1 -1 -1" diffuse="0.4 0.4 0.4" />
  <body name="obj_0" pos="-1.1291666873329838 0.6163637941061021 0.13728315865007457" quat="-0.0005200170863228699 -0.9999757066832461 -0.00694223910940556 0.00034776676130889516"><joint name="freejoint_0" type="free" /><inertial pos="0 0 0" mass="1.0" diaginertia="0.001 0.001 0.001" /><geom name="obj_geom_0" type="mesh" mesh="obj_0" rgba="0.8 0.6 0.2 1" friction="0.7 0.01 0.01" /></body><body name="obj_1" pos="-1.030717258312969 -1.3258135809392408 0.13388484165998876" quat="0.999940525221108 0.000591113734949708 0.01088244998262704 0.00041095919645562463"><joint name="freejoint_1" type="free" /><inertial pos="0 0 0" mass="1.0" diaginertia="0.001 0.001 0.001" /><geom name="obj_geom_1" type="mesh" mesh="obj_1" rgba="0.8 0.6 0.2 1" friction="0.7 0.01 0.01" /></body><body name="obj_2" pos="-0.8182674591221702 -0.6802309146376538 0.13601521102044126" quat="0.0010599547898933184 0.25878690373516405 -0.9659337174544033 0.0005181078337402707"><joint name="freejoint_2" type="free" /><inertial pos="0 0 0" mass="1.0" diaginertia="0.001 0.001 0.001" /><geom name="obj_geom_2" type="mesh" mesh="obj_2" rgba="0.8 0.6 0.2 1" friction="0.7 0.01 0.01" /></body><body name="obj_3" pos="0.11625669438798873 -0.9018689325301157 -0.10355809307097294" quat="0.8635720912046787 0.011762444319056996 -0.04282671201620057 0.5022656278642803"><joint name="freejoint_3" type="free" /><inertial pos="0 0 0" mass="1.0" diaginertia="0.001 0.001 0.001" /><geom name="obj_geom_3" type="mesh" mesh="obj_3" rgba="0.8 0.6 0.2 1" friction="0.7 0.01 0.01" /></body><body name="obj_4" pos="3.29292406676335 2.1778487754676195 -0.4007299724067266" quat="-0.7766190433444795 -0.4171011013197886 0.22346130872788691 0.41587807864101795"><joint name="freejoint_4" type="free" /><inertial pos="0 0 0" mass="1.0" diaginertia="0.001 0.001 0.001" /><geom name="obj_geom_4" type="mesh" mesh="obj_4" rgba="0.8 0.6 0.2 1" friction="0.7 0.01 0.01" /></body><body name="obj_5" pos="1.3325084204300113 -0.682384734702602 -0.008967058543427867" quat="0.9765608168892382 0.0013226060101645403 0.0003223014036249205 0.215237352129623"><joint name="freejoint_5" type="free" /><inertial pos="0 0 0" mass="1.0" diaginertia="0.001 0.001 0.001" /><geom name="obj_geom_5" type="mesh" mesh="obj_5" rgba="0.8 0.6 0.2 1" friction="0.7 0.01 0.01" /></body><body name="obj_6" pos="0.8700801368407103 -0.8885040376626255 0.014522783346607225" quat="0.0002632412727564779 0.5638089945997384 -0.8259051554574313 0.00015000433548732268"><joint name="freejoint_6" type="free" /><inertial pos="0 0 0" mass="1.0" diaginertia="0.001 0.001 0.001" /><geom name="obj_geom_6" type="mesh" mesh="obj_6" rgba="0.8 0.6 0.2 1" friction="0.7 0.01 0.01" /></body><body name="obj_7" pos="0.8874458916029826 -0.6451228298935089 -0.05524640894386643" quat="0.6893787654333103 -0.13581736704265235 -0.6984453180320644 -0.13595844327710116"><joint name="freejoint_7" type="free" /><inertial pos="0 0 0" mass="1.0" diaginertia="0.001 0.001 0.001" /><geom name="obj_geom_7" type="mesh" mesh="obj_7" rgba="0.8 0.6 0.2 1" friction="0.7 0.01 0.01" /></body><body name="obj_8" pos="0.9998203667351273 -1.3581445948674875 0.2652508350872402" quat="0.7065762834228977 -0.01626180101385422 -0.013713199689448799 -0.7073170842601983"><joint name="freejoint_8" type="free" /><inertial pos="0 0 0" mass="1.0" diaginertia="0.001 0.001 0.001" /><geom name="obj_geom_8" type="mesh" mesh="obj_8" rgba="0.8 0.6 0.2 1" friction="0.7 0.01 0.01" /></body><body name="obj_9" pos="1.2114767416956338 2.724307367261955 0.2597505578418874" quat="-0.3647154765996984 0.6057037139777106 0.3648076651033275 0.6058225808635073"><joint name="freejoint_9" type="free" /><inertial pos="0 0 0" mass="1.0" diaginertia="0.001 0.001 0.001" /><geom name="obj_geom_9" type="mesh" mesh="obj_9" rgba="0.8 0.6 0.2 1" friction="0.7 0.01 0.01" /></body><body name="obj_10" pos="1.1459092606495846 0.5339832050687134 -0.0022082239386628107" quat="-0.6894942880413348 -0.0011445118903023683 -0.0015131747521000248 -0.72428863525053"><joint name="freejoint_10" type="free" /><inertial pos="0 0 0" mass="1.0" diaginertia="0.001 0.001 0.001" /><geom name="obj_geom_10" type="mesh" mesh="obj_10" rgba="0.8 0.6 0.2 1" friction="0.7 0.01 0.01" /></body><body name="obj_11" pos="-1.0918079973657604 -0.057788697517660956 -1.562154393037942e-05" quat="0.6142521611036047 0.0006719721080662069 0.0008629223933226096 -0.7891090459486446"><joint name="freejoint_11" type="free" /><inertial pos="0 0 0" mass="1.0" diaginertia="0.001 0.001 0.001" /><geom name="obj_geom_11" type="mesh" mesh="obj_11" rgba="0.8 0.6 0.2 1" friction="0.7 0.01 0.01" /></body><body name="obj_12" pos="0.5852286001850638 0.5075877472208762 0.28339278883238045" quat="-0.2702211873450592 -0.7065834476255496 0.02035034332678318 0.6536866259744809"><joint name="freejoint_12" type="free" /><inertial pos="0 0 0" mass="1.0" diaginertia="0.001 0.001 0.001" /><geom name="obj_geom_12" type="mesh" mesh="obj_12" rgba="0.8 0.6 0.2 1" friction="0.7 0.01 0.01" /></body><body name="obj_13" pos="1.312915078331442 0.10167002765609806 0.17658059273794463" quat="0.6674822114337899 -0.5829715829920588 -0.40038107747913926 -0.23303781590083816"><joint name="freejoint_13" type="free" /><inertial pos="0 0 0" mass="1.0" diaginertia="0.001 0.001 0.001" /><geom name="obj_geom_13" type="mesh" mesh="obj_13" rgba="0.8 0.6 0.2 1" friction="0.7 0.01 0.01" /></body><body name="obj_14" pos="1.3118051301285922 0.15847043794212304 -2.1026637431751315e-05" quat="0.6382493030596318 0.0009862894625393306 0.0010770152665544293 0.7698283538653973"><joint name="freejoint_14" type="free" /><inertial pos="0 0 0" mass="1.0" diaginertia="0.001 0.001 0.001" /><geom name="obj_geom_14" type="mesh" mesh="obj_14" rgba="0.8 0.6 0.2 1" friction="0.7 0.01 0.01" /></body><body name="obj_15" pos="7.696005144997132 -6.082410609418289 0.07625551447643243" quat="0.7007004945052895 0.15785673291861427 0.6897362447860597 -0.0914548057825767"><joint name="freejoint_15" type="free" /><inertial pos="0 0 0" mass="1.0" diaginertia="0.001 0.001 0.001" /><geom name="obj_geom_15" type="mesh" mesh="obj_15" rgba="0.8 0.6 0.2 1" friction="0.7 0.01 0.01" /></body><body name="obj_16" pos="1.033765975367613 -3.237783609141407 0.6198476184411257" quat="-2.0922882640094284e-05 -0.24779288403997768 -0.9688130292578807 2.2837529737622327e-05"><joint name="freejoint_16" type="free" /><inertial pos="0 0 0" mass="1.0" diaginertia="0.001 0.001 0.001" /><geom name="obj_geom_16" type="mesh" mesh="obj_16" rgba="0.8 0.6 0.2 1" friction="0.7 0.01 0.01" /></body><body name="obj_17" pos="-0.13449575555478638 -0.2129386316009814 -0.05342787455342823" quat="0.6572148815343076 -0.2713007010552908 -0.6480882450637085 -0.27284822833765493"><joint name="freejoint_17" type="free" /><inertial pos="0 0 0" mass="1.0" diaginertia="0.001 0.001 0.001" /><geom name="obj_geom_17" type="mesh" mesh="obj_17" rgba="0.8 0.6 0.2 1" friction="0.7 0.01 0.01" /></body><body name="obj_18" pos="-4.031966877642201 -0.052700390072530405 0.8496730172183297" quat="-0.00014751801660623846 -0.9879684248988476 -0.1546556441749104 3.6961713547585887e-05"><joint name="freejoint_18" type="free" /><inertial pos="0 0 0" mass="1.0" diaginertia="0.001 0.001 0.001" /><geom name="obj_geom_18" type="mesh" mesh="obj_18" rgba="0.8 0.6 0.2 1" friction="0.7 0.01 0.01" /></body><body name="obj_19" pos="-0.31374796643662284 -1.0589375892628006 0.46427211179739797" quat="0.4576722194947968 -0.43856694341855657 -0.5350043522973794 -0.5585387351527855"><joint name="freejoint_19" type="free" /><inertial pos="0 0 0" mass="1.0" diaginertia="0.001 0.001 0.001" /><geom name="obj_geom_19" type="mesh" mesh="obj_19" rgba="0.8 0.6 0.2 1" friction="0.7 0.01 0.01" /></body><body name="obj_20" pos="2.4442030782062014 5.113186818211977 -0.40064173262191866" quat="0.5155522326553246 0.2769536650479986 -0.3837450046425012 -0.7143124906037395"><joint name="freejoint_20" type="free" /><inertial pos="0 0 0" mass="1.0" diaginertia="0.001 0.001 0.001" /><geom name="obj_geom_20" type="mesh" mesh="obj_20" rgba="0.8 0.6 0.2 1" friction="0.7 0.01 0.01" /></body><body name="obj_21" pos="-2.4023352220072423 -0.4129536772028985 0.12167074542438916" quat="-0.2673325494703438 -0.0522310234810238 -0.010584824713442808 -0.9621295077408215"><joint name="freejoint_21" type="free" /><inertial pos="0 0 0" mass="1.0" diaginertia="0.001 0.001 0.001" /><geom name="obj_geom_21" type="mesh" mesh="obj_21" rgba="0.8 0.6 0.2 1" friction="0.7 0.01 0.01" /></body></worldbody>
</mujoco>